spgmiciq/__init__.py
spgmiciq-2.0.0.dist-info/METADATA
spgmiciq-2.0.0.dist-info/WHEEL
spgmiciq-2.0.0.dist-info/RECORD
